tg_api_autoreg/__init__.py
tg_api_autoreg-0.1.3.dist-info/METADATA
tg_api_autoreg-0.1.3.dist-info/WHEEL
tg_api_autoreg-0.1.3.dist-info/top_level.txt
tg_api_autoreg-0.1.3.dist-info/RECORD
