Metadata-Version: 2.1
Name: tg-api-autoreg
Version: 0.1.3
Summary: Library for automatic registration telegram User Api (Alpha)
Home-page: https://github.com/youbrain/tg_user_api_autoreg
Author: Alexandr Macheck
Author-email: 647533sancho@gmail.com
License: UNKNOWN
Platform: UNKNOWN
Requires-Dist: requests
